mlease/__init__.py
mlease/bucketizer.py
mlease/missing_value_imputer.py
mlease/outlier_remover.py
MLEase-0.0.2.dist-info/LICENSE.txt
MLEase-0.0.2.dist-info/METADATA
MLEase-0.0.2.dist-info/WHEEL
MLEase-0.0.2.dist-info/top_level.txt
MLEase-0.0.2.dist-info/RECORD
