Metadata-Version: 2.1
Name: MLEase
Version: 0.0.2
Summary: Simplify machine learning tasks with easy-to-use tools and utilities.
Home-page: https://github.com/harikrishnad1997/MLEase
Author: Harikrishna Dev
Author-email: harikrish0607@gmail.com
Keywords: python,machine learning,data science
Classifier: Development Status :: 3 - Alpha
Classifier: Intended Audience :: Developers
Classifier: Intended Audience :: Education
Classifier: Intended Audience :: Science/Research
Classifier: License :: OSI Approved :: MIT License
Classifier: Programming Language :: Python :: 3.8
Classifier: Programming Language :: Python :: 3.9
Classifier: Operating System :: OS Independent
License-File: LICENSE.txt
Requires-Dist: scikit-learn
Requires-Dist: pandas
Requires-Dist: numpy
Requires-Dist: joblib
Requires-Dist: python-dateutil
Requires-Dist: pytz
Requires-Dist: six
Requires-Dist: threadpoolctl
Requires-Dist: xgbimputer
Requires-Dist: xgboost
